tem/__init__.py
tem/__main__.py
tem/add.py
tem/common.py
tem/config.py
tem/ext.py
tem/ls.py
tem/put.py
tem/repo.py
tem/rm.py
tem-0.0.0.dist-info/METADATA
tem-0.0.0.dist-info/WHEEL
tem-0.0.0.dist-info/entry_points.txt
tem-0.0.0.dist-info/top_level.txt
tem-0.0.0.dist-info/RECORD
