Metadata-Version: 2.1
Name: tem
Version: 0.0.0
Summary: Don't Repeat Yourself. Seriously.
Home-page: https://github.com/harisgusic/tem
Author: Haris Gušić
Author-email: harisgusic.dev@gmail.com
License: UNKNOWN
Platform: UNKNOWN
Classifier: Programming Language :: Python :: 3.9
